g2p/__init__.py
g2p/_version.py
g2p/api.py
g2p/api_v2.py
g2p/app.py
g2p/cli.py
g2p/constants.py
g2p/exceptions.py
g2p/log.py
g2p/shared_types.py
g2p/mappings/__init__.py
g2p/mappings/create_fallback_mapping.py
g2p/mappings/create_ipa_mapping.py
g2p/mappings/tokenizer.py
g2p/mappings/utils.py
g2p/mappings/.schema/g2p-config-schema-2.0.json
g2p/mappings/.schema/g2p-config-schema-2.1.json
g2p/mappings/.schema/g2p-config-schema-2.2.json
g2p/mappings/langs/__init__.py
g2p/mappings/langs/langs.json.gz
g2p/mappings/langs/network.json.gz
g2p/mappings/langs/network_lite.py
g2p/mappings/langs/utils.py
g2p/mappings/langs/alq/alq_to_ipa.csv
g2p/mappings/langs/alq/config-g2p.yaml
g2p/mappings/langs/atj/README.md
g2p/mappings/langs/atj/atj_ipa_to_eng_ipa.json
g2p/mappings/langs/atj/atj_to_ipa.json
g2p/mappings/langs/atj/config-g2p.yaml
g2p/mappings/langs/ckt/README.md
g2p/mappings/langs/ckt/ckt_ipa_to_eng_ipa.json
g2p/mappings/langs/ckt/ckt_to_ipa.json
g2p/mappings/langs/ckt/config-g2p.yaml
g2p/mappings/langs/clc/config-g2p.yaml
g2p/mappings/langs/clc/doulos.csv
g2p/mappings/langs/clm/clm_equiv.csv
g2p/mappings/langs/clm/clm_to_ipa.csv
g2p/mappings/langs/clm/config-g2p.yaml
g2p/mappings/langs/crg/abbreviations.csv
g2p/mappings/langs/crg/config-g2p.yaml
g2p/mappings/langs/crg/crg-dv-to-crg-ipa.csv
g2p/mappings/langs/crg/crg-tmd-to-crg-ipa.csv
g2p/mappings/langs/crj/README.md
g2p/mappings/langs/crj/config-g2p.yaml
g2p/mappings/langs/crj/crj_equiv.json
g2p/mappings/langs/crj/crj_ipa_to_eng_ipa.json
g2p/mappings/langs/crj/crj_to_ipa.json
g2p/mappings/langs/crk/README.md
g2p/mappings/langs/crk/config-g2p.yaml
g2p/mappings/langs/crk/crk-no-symbols_to_ipa.json
g2p/mappings/langs/crk/crk_to_crk-no-symbols.json
g2p/mappings/langs/crl/README.md
g2p/mappings/langs/crl/config-g2p.yaml
g2p/mappings/langs/crl/crl_equiv.json
g2p/mappings/langs/crl/crl_ipa_to_eng_ipa.json
g2p/mappings/langs/crl/crl_to_ipa.json
g2p/mappings/langs/crm/README.md
g2p/mappings/langs/crm/config-g2p.yaml
g2p-2.2.2.dist-info/METADATA
g2p-2.2.2.dist-info/WHEEL
g2p-2.2.2.dist-info/entry_points.txt
g2p-2.2.2.dist-info/licenses/LICENSE
g2p-2.2.2.dist-info/RECORD
