Metadata-Version: 2.4
Name: g2p
Version: 2.2.2
Summary: Module for creating context-aware, rule-based G2P mappings that preserve indices
Project-URL: Homepage, https://github.com/roedoejet/g2p
Author-email: Aidan Pine <hello@aidanpine.ca>
License-Expression: MIT
License-File: LICENSE
Classifier: License :: OSI Approved :: MIT License
Classifier: Operating System :: OS Independent
Classifier: Programming Language :: Python :: 3
Requires-Python: >=3.7
Requires-Dist: click<8.2.0,>=8.0.4
Requires-Dist: coloredlogs>=15.0.1
Requires-Dist: openpyxl
Requires-Dist: panphon<0.21; platform_system == 'Windows'
Requires-Dist: panphon<0.21; python_version < '3.9'
Requires-Dist: panphon<0.22; python_version < '3.10'
Requires-Dist: panphon>=0.19
Requires-Dist: pydantic<2.9,>=2.4
Requires-Dist: pyyaml>=5.2
Requires-Dist: regex
Requires-Dist: text-unidecode
Requires-Dist: tqdm
Requires-Dist: typing-extensions
Provides-Extra: api
Requires-Dist: fastapi>=0.109.0; extra == 'api'
Requires-Dist: jinja2; extra == 'api'
Requires-Dist: python-socketio>=5.9.0; extra == 'api'
Requires-Dist: starlette>=0.40.0; extra == 'api'
Requires-Dist: uvicorn; extra == 'api'
Provides-Extra: dev
Requires-Dist: aiohttp; extra == 'dev'
Requires-Dist: coverage[toml]>=6.5; extra == 'dev'
Requires-Dist: fastapi>=0.109.0; extra == 'dev'
Requires-Dist: gitlint-core>=0.17.0; extra == 'dev'
Requires-Dist: httpx; extra == 'dev'
Requires-Dist: jinja2; extra == 'dev'
Requires-Dist: jsonschema>=4.17.3; extra == 'dev'
Requires-Dist: mypy>=1.8.0; (python_version >= '3.8') and extra == 'dev'
Requires-Dist: mypy>=1; (python_version < '3.8') and extra == 'dev'
Requires-Dist: pep440>=0.1.2; extra == 'dev'
Requires-Dist: playwright<1.46,>=1.26.1; (python_version < '3.9') and extra == 'dev'
Requires-Dist: playwright>=1.26.1; (python_version >= '3.9') and extra == 'dev'
Requires-Dist: pre-commit>=3.2.0; (python_version >= '3.8') and extra == 'dev'
Requires-Dist: python-socketio>=5.9.0; extra == 'dev'
Requires-Dist: starlette>=0.40.0; extra == 'dev'
Requires-Dist: uvicorn; extra == 'dev'
Provides-Extra: docs
Requires-Dist: mike>=1.1.2; extra == 'docs'
Requires-Dist: mkdocs-click>=0.8.0; extra == 'docs'
Requires-Dist: mkdocs-material>=9.2.5; extra == 'docs'
Requires-Dist: mkdocs>=1.5.2; extra == 'docs'
Requires-Dist: mkdocstrings[python]>=0.22.0; extra == 'docs'
Provides-Extra: prod
Requires-Dist: gunicorn>=22.0.0; extra == 'prod'
Provides-Extra: test
Requires-Dist: aiohttp; extra == 'test'
Requires-Dist: coverage[toml]>=6.5; extra == 'test'
Requires-Dist: fastapi>=0.109.0; extra == 'test'
Requires-Dist: httpx; extra == 'test'
Requires-Dist: jinja2; extra == 'test'
Requires-Dist: jsonschema>=4.17.3; extra == 'test'
Requires-Dist: pep440>=0.1.2; extra == 'test'
Requires-Dist: playwright<1.46,>=1.26.1; (python_version < '3.9') and extra == 'test'
Requires-Dist: playwright>=1.26.1; (python_version >= '3.9') and extra == 'test'
Requires-Dist: python-socketio>=5.9.0; extra == 'test'
Requires-Dist: starlette>=0.40.0; extra == 'test'
Requires-Dist: uvicorn; extra == 'test'
